{
  "client" : {
    "name" : "clientPoolC"
  },
  "request" : {
    "startTime" : 450000,
    "networkDuration" : 500000,
    "service" : {
      "group" : "com.bbn",
      "artifact" : "test-service2",
      "version" : "1"
    },
    "networkLoad" : {
      "DATARATE_TX" : 0.001,
      "DATARATE_RX" : 0.002
    },
    "serverDuration" : 500000,
    "nodeLoad" : {
      "TASK_CONTAINERS" : 0.1
    },
    "numClients" : 20
  },
  "timeReceived" : 450402,
  "status" : "SUCCESS",
  "load" : {
    "TASK_CONTAINERS" : 0.1
  },
  "serverCapacity" : {
    "CPU" : 1.0,
    "TASK_CONTAINERS" : 1.0,
    "QueueLength" : 1000000.0
  }
}{
  "client" : {
    "name" : "clientPoolC"
  },
  "request" : {
    "startTime" : 450000,
    "networkDuration" : 500000,
    "service" : {
      "group" : "com.bbn",
      "artifact" : "test-service2",
      "version" : "1"
    },
    "networkLoad" : {
      "DATARATE_TX" : 0.001,
      "DATARATE_RX" : 0.002
    },
    "serverDuration" : 500000,
    "nodeLoad" : {
      "TASK_CONTAINERS" : 0.1
    },
    "numClients" : 20
  },
  "timeReceived" : 450507,
  "status" : "SUCCESS",
  "load" : {
    "TASK_CONTAINERS" : 0.2
  },
  "serverCapacity" : {
    "CPU" : 1.0,
    "TASK_CONTAINERS" : 1.0,
    "QueueLength" : 1000000.0
  }
}{
  "client" : {
    "name" : "clientPoolC"
  },
  "request" : {
    "startTime" : 450000,
    "networkDuration" : 500000,
    "service" : {
      "group" : "com.bbn",
      "artifact" : "test-service2",
      "version" : "1"
    },
    "networkLoad" : {
      "DATARATE_TX" : 0.001,
      "DATARATE_RX" : 0.002
    },
    "serverDuration" : 500000,
    "nodeLoad" : {
      "TASK_CONTAINERS" : 0.1
    },
    "numClients" : 20
  },
  "timeReceived" : 450552,
  "status" : "SUCCESS",
  "load" : {
    "TASK_CONTAINERS" : 0.30000000000000004
  },
  "serverCapacity" : {
    "CPU" : 1.0,
    "TASK_CONTAINERS" : 1.0,
    "QueueLength" : 1000000.0
  }
}{
  "client" : {
    "name" : "clientPoolC"
  },
  "request" : {
    "startTime" : 450000,
    "networkDuration" : 500000,
    "service" : {
      "group" : "com.bbn",
      "artifact" : "test-service2",
      "version" : "1"
    },
    "networkLoad" : {
      "DATARATE_TX" : 0.001,
      "DATARATE_RX" : 0.002
    },
    "serverDuration" : 500000,
    "nodeLoad" : {
      "TASK_CONTAINERS" : 0.1
    },
    "numClients" : 20
  },
  "timeReceived" : 450949,
  "status" : "SUCCESS",
  "load" : {
    "TASK_CONTAINERS" : 0.4
  },
  "serverCapacity" : {
    "CPU" : 1.0,
    "TASK_CONTAINERS" : 1.0,
    "QueueLength" : 1000000.0
  }
}{
  "client" : {
    "name" : "clientPoolC"
  },
  "request" : {
    "startTime" : 510000,
    "networkDuration" : 500000,
    "service" : {
      "group" : "com.bbn",
      "artifact" : "test-service2",
      "version" : "1"
    },
    "networkLoad" : {
      "DATARATE_TX" : 0.001,
      "DATARATE_RX" : 0.002
    },
    "serverDuration" : 500000,
    "nodeLoad" : {
      "TASK_CONTAINERS" : 0.1
    },
    "numClients" : 20
  },
  "timeReceived" : 512228,
  "status" : "SUCCESS",
  "load" : {
    "TASK_CONTAINERS" : 0.5
  },
  "serverCapacity" : {
    "CPU" : 1.0,
    "TASK_CONTAINERS" : 1.0,
    "QueueLength" : 1000000.0
  }
}{
  "client" : {
    "name" : "clientPoolC"
  },
  "request" : {
    "startTime" : 510000,
    "networkDuration" : 500000,
    "service" : {
      "group" : "com.bbn",
      "artifact" : "test-service2",
      "version" : "1"
    },
    "networkLoad" : {
      "DATARATE_TX" : 0.001,
      "DATARATE_RX" : 0.002
    },
    "serverDuration" : 500000,
    "nodeLoad" : {
      "TASK_CONTAINERS" : 0.1
    },
    "numClients" : 20
  },
  "timeReceived" : 512481,
  "status" : "SUCCESS",
  "load" : {
    "TASK_CONTAINERS" : 0.6
  },
  "serverCapacity" : {
    "CPU" : 1.0,
    "TASK_CONTAINERS" : 1.0,
    "QueueLength" : 1000000.0
  }
}{
  "client" : {
    "name" : "clientPoolC"
  },
  "request" : {
    "startTime" : 570000,
    "networkDuration" : 500000,
    "service" : {
      "group" : "com.bbn",
      "artifact" : "test-service2",
      "version" : "1"
    },
    "networkLoad" : {
      "DATARATE_TX" : 0.001,
      "DATARATE_RX" : 0.002
    },
    "serverDuration" : 500000,
    "nodeLoad" : {
      "TASK_CONTAINERS" : 0.1
    },
    "numClients" : 20
  },
  "timeReceived" : 571214,
  "status" : "SUCCESS",
  "load" : {
    "TASK_CONTAINERS" : 0.7
  },
  "serverCapacity" : {
    "CPU" : 1.0,
    "TASK_CONTAINERS" : 1.0,
    "QueueLength" : 1000000.0
  }
}